[
    {
        "kind": "warn",
        "message": "郵便番号の形式ではありません index:2 col:2 value:",
        "page": 1,
        "path": "C:\\dev\\python3\\yakusyopdf/latest/茨城県.pdf"
    },
    {
        "kind": "warn",
        "message": "値が存在しません. index:2 col:3 value:",
        "page": 1,
        "path": "C:\\dev\\python3\\yakusyopdf/latest/茨城県.pdf"
    },
    {
        "kind": "warn",
        "message": "値が存在しません. index:2 col:4 value:",
        "page": 1,
        "path": "C:\\dev\\python3\\yakusyopdf/latest/茨城県.pdf"
    },
    {
        "kind": "warn",
        "message": "郵便番号の形式ではありません index:7 col:2 value:32-0022",
        "page": 4,
        "path": "C:\\dev\\python3\\yakusyopdf/latest/茨城県.pdf"
    },
    {
        "kind": "warn",
        "message": "値が存在しません. index:0 col:1 value:",
        "page": 9,
        "path": "C:\\dev\\python3\\yakusyopdf/latest/茨城県.pdf"
    },
    {
        "kind": "warn",
        "message": "郵便番号の形式ではありません index:0 col:2 value:",
        "page": 9,
        "path": "C:\\dev\\python3\\yakusyopdf/latest/茨城県.pdf"
    },
    {
        "kind": "warn",
        "message": "値が存在しません. index:0 col:3 value:",
        "page": 9,
        "path": "C:\\dev\\python3\\yakusyopdf/latest/茨城県.pdf"
    },
    {
        "kind": "warn",
        "message": "値が存在しません. index:0 col:4 value:",
        "page": 9,
        "path": "C:\\dev\\python3\\yakusyopdf/latest/茨城県.pdf"
    },
    {
        "kind": "warn",
        "message": "郵便番号の形式ではありません index:8 col:2 value:",
        "page": 9,
        "path": "C:\\dev\\python3\\yakusyopdf/latest/茨城県.pdf"
    },
    {
        "kind": "warn",
        "message": "値が存在しません. index:8 col:3 value:",
        "page": 9,
        "path": "C:\\dev\\python3\\yakusyopdf/latest/茨城県.pdf"
    },
    {
        "kind": "warn",
        "message": "値が存在しません. index:8 col:4 value:",
        "page": 9,
        "path": "C:\\dev\\python3\\yakusyopdf/latest/茨城県.pdf"
    },
    {
        "kind": "warn",
        "message": "郵便番号の形式ではありません index:1 col:2 value:",
        "page": 11,
        "path": "C:\\dev\\python3\\yakusyopdf/latest/茨城県.pdf"
    },
    {
        "kind": "warn",
        "message": "値が存在しません. index:1 col:3 value:",
        "page": 11,
        "path": "C:\\dev\\python3\\yakusyopdf/latest/茨城県.pdf"
    },
    {
        "kind": "warn",
        "message": "値が存在しません. index:1 col:4 value:",
        "page": 11,
        "path": "C:\\dev\\python3\\yakusyopdf/latest/茨城県.pdf"
    },
    {
        "kind": "warn",
        "message": "郵便番号の形式ではありません index:10 col:2 value:",
        "page": 11,
        "path": "C:\\dev\\python3\\yakusyopdf/latest/茨城県.pdf"
    },
    {
        "kind": "warn",
        "message": "値が存在しません. index:10 col:3 value:",
        "page": 11,
        "path": "C:\\dev\\python3\\yakusyopdf/latest/茨城県.pdf"
    },
    {
        "kind": "warn",
        "message": "値が存在しません. index:10 col:4 value:",
        "page": 11,
        "path": "C:\\dev\\python3\\yakusyopdf/latest/茨城県.pdf"
    },
    {
        "kind": "warn",
        "message": "郵便番号の形式ではありません index:7 col:2 value:",
        "page": 12,
        "path": "C:\\dev\\python3\\yakusyopdf/latest/茨城県.pdf"
    },
    {
        "kind": "warn",
        "message": "値が存在しません. index:7 col:3 value:",
        "page": 12,
        "path": "C:\\dev\\python3\\yakusyopdf/latest/茨城県.pdf"
    },
    {
        "kind": "warn",
        "message": "値が存在しません. index:7 col:4 value:",
        "page": 12,
        "path": "C:\\dev\\python3\\yakusyopdf/latest/茨城県.pdf"
    },
    {
        "kind": "warn",
        "message": "郵便番号の形式ではありません index:14 col:2 value:",
        "page": 13,
        "path": "C:\\dev\\python3\\yakusyopdf/latest/茨城県.pdf"
    },
    {
        "kind": "warn",
        "message": "値が存在しません. index:14 col:3 value:",
        "page": 13,
        "path": "C:\\dev\\python3\\yakusyopdf/latest/茨城県.pdf"
    },
    {
        "kind": "warn",
        "message": "値が存在しません. index:14 col:4 value:",
        "page": 13,
        "path": "C:\\dev\\python3\\yakusyopdf/latest/茨城県.pdf"
    },
    {
        "kind": "warn",
        "message": "郵便番号の形式ではありません index:10 col:2 value:",
        "page": 14,
        "path": "C:\\dev\\python3\\yakusyopdf/latest/茨城県.pdf"
    },
    {
        "kind": "warn",
        "message": "値が存在しません. index:10 col:3 value:",
        "page": 14,
        "path": "C:\\dev\\python3\\yakusyopdf/latest/茨城県.pdf"
    },
    {
        "kind": "warn",
        "message": "値が存在しません. index:10 col:4 value:",
        "page": 14,
        "path": "C:\\dev\\python3\\yakusyopdf/latest/茨城県.pdf"
    },
    {
        "kind": "warn",
        "message": "郵便番号の形式ではありません index:6 col:2 value:",
        "page": 17,
        "path": "C:\\dev\\python3\\yakusyopdf/latest/茨城県.pdf"
    },
    {
        "kind": "warn",
        "message": "値が存在しません. index:6 col:3 value:",
        "page": 17,
        "path": "C:\\dev\\python3\\yakusyopdf/latest/茨城県.pdf"
    },
    {
        "kind": "warn",
        "message": "値が存在しません. index:6 col:4 value:",
        "page": 17,
        "path": "C:\\dev\\python3\\yakusyopdf/latest/茨城県.pdf"
    },
    {
        "kind": "warn",
        "message": "値が存在しません. index:0 col:1 value:",
        "page": 19,
        "path": "C:\\dev\\python3\\yakusyopdf/latest/茨城県.pdf"
    },
    {
        "kind": "warn",
        "message": "郵便番号の形式ではありません index:0 col:2 value:",
        "page": 19,
        "path": "C:\\dev\\python3\\yakusyopdf/latest/茨城県.pdf"
    },
    {
        "kind": "warn",
        "message": "値が存在しません. index:0 col:3 value:",
        "page": 19,
        "path": "C:\\dev\\python3\\yakusyopdf/latest/茨城県.pdf"
    },
    {
        "kind": "warn",
        "message": "値が存在しません. index:0 col:4 value:",
        "page": 19,
        "path": "C:\\dev\\python3\\yakusyopdf/latest/茨城県.pdf"
    },
    {
        "kind": "warn",
        "message": "郵便番号の形式ではありません index:9 col:2 value:",
        "page": 19,
        "path": "C:\\dev\\python3\\yakusyopdf/latest/茨城県.pdf"
    },
    {
        "kind": "warn",
        "message": "値が存在しません. index:9 col:3 value:",
        "page": 19,
        "path": "C:\\dev\\python3\\yakusyopdf/latest/茨城県.pdf"
    },
    {
        "kind": "warn",
        "message": "値が存在しません. index:9 col:4 value:",
        "page": 19,
        "path": "C:\\dev\\python3\\yakusyopdf/latest/茨城県.pdf"
    },
    {
        "kind": "warn",
        "message": "値が存在しません. index:7 col:4 value:",
        "page": 21,
        "path": "C:\\dev\\python3\\yakusyopdf/latest/茨城県.pdf"
    },
    {
        "kind": "info",
        "message": "telが空のためurlから値を取得しました. url:029-858-9590http://www.k.tsukuba-tech.ac.jp/cl/->029-858-9590, http://www.k.tsukuba-tech.ac.jp/cl/",
        "page": 21,
        "path": "C:\\dev\\python3\\yakusyopdf/latest/茨城県.pdf"
    },
    {
        "kind": "warn",
        "message": "郵便番号の形式ではありません index:9 col:2 value:",
        "page": 22,
        "path": "C:\\dev\\python3\\yakusyopdf/latest/茨城県.pdf"
    },
    {
        "kind": "warn",
        "message": "値が存在しません. index:9 col:3 value:",
        "page": 22,
        "path": "C:\\dev\\python3\\yakusyopdf/latest/茨城県.pdf"
    },
    {
        "kind": "warn",
        "message": "値が存在しません. index:9 col:4 value:",
        "page": 22,
        "path": "C:\\dev\\python3\\yakusyopdf/latest/茨城県.pdf"
    },
    {
        "kind": "warn",
        "message": "郵便番号の形式ではありません index:0 col:2 value:",
        "page": 24,
        "path": "C:\\dev\\python3\\yakusyopdf/latest/茨城県.pdf"
    },
    {
        "kind": "warn",
        "message": "値が存在しません. index:0 col:3 value:",
        "page": 24,
        "path": "C:\\dev\\python3\\yakusyopdf/latest/茨城県.pdf"
    },
    {
        "kind": "warn",
        "message": "値が存在しません. index:0 col:4 value:",
        "page": 24,
        "path": "C:\\dev\\python3\\yakusyopdf/latest/茨城県.pdf"
    }
]